AugustBetty/CharBestGroup.py
AugustBetty/ChiMergeGroup.py
AugustBetty/GetDiffDays.py
AugustBetty/ModelMain.py
AugustBetty/NumBestGroup.py
AugustBetty/__init__.py
AugustBetty/valueCounts.py
AugustBetty-1.1.1.dist-info/METADATA
AugustBetty-1.1.1.dist-info/WHEEL
AugustBetty-1.1.1.dist-info/top_level.txt
AugustBetty-1.1.1.dist-info/zip-safe
AugustBetty-1.1.1.dist-info/RECORD
