Metadata-Version: 2.1
Name: AugustBetty
Version: 1.1.1
Summary: 这是一个用来做逻辑回归全自动开发评分卡的包，支持数值，字符变量的最优分组。
Home-page: https://github.com/XueRenJing
Author: BettyZhan
Author-email: 438074342@qq.com
License: MIT
Keywords: python package Logistic regression  model
Platform: UNKNOWN
Classifier: License :: OSI Approved :: MIT License
Classifier: Programming Language :: Python
Classifier: Intended Audience :: Developers
Classifier: Operating System :: OS Independent
